README.md
setup.py
cimese_net/__init__.py
cimese_net.egg-info/PKG-INFO
cimese_net.egg-info/SOURCES.txt
cimese_net.egg-info/dependency_links.txt
cimese_net.egg-info/not-zip-safe
cimese_net.egg-info/requires.txt
cimese_net.egg-info/top_level.txt
cimese_net/data/Neg_AllFrames.data
cimese_net/data/Pos_AllFrames.data
cimese_net/data/Test_AllFrames.data
cimese_net/data/cimese_net_best_model.h5