Metadata-Version: 1.0
Name: cimese_net
Version: 0.37
Summary: Basic implementation of a Siamese network structure for detecting copyright infringement
Home-page: http://github.com/doughertyeric/cimese_net
Author: Eric Dougherty
Author-email: dougherty.eric@gmail.com
License: UNKNOWN
Platform: UNKNOWN
